{
    "openapi": "3.0.0",
    "info": {
        "title": "Ora Hydric Documentation",
        "description": "This is an API for the Ora Hydric Module",
        "version": "1.0.0",
        "contact": {
            "email": "administrativo@geodatin.com"
        }
    },
    "servers": [
        {
            "url": "/api"
        }
    ],
    "paths": {
        "/territory/{name}": {
            "get": {
                "tags": [
                    "Territory"
                ],
                "parameters": [
                    {
                        "name": "name",
                        "in": "path",
                        "description": "Search string for the territory",
                        "required": true,
                        "schema": {
                            "type": "string"
                        }
                    }
                ],
                "summary": "List categories",
                "description": "List all created categories",
                "responses": {
                    "200": {
                        "description": "Success",
                        "content": {
                            "application/json": {
                                "schema": {
                                    "type": "array",
                                    "items": {
                                        "type": "object",
                                        "properties": {
                                            "name": {
                                                "type": "string"
                                            },
                                            "description": {
                                                "type": "string"
                                            }
                                        }
                                    }
                                }
                            }
                        }
                    }
                }
            }
        }
    },
    "definitions": {},
    "components": {}
}